multimatch/__init__.py
multimatch/__main__.py
multimatch/multimatch.py
multimatch/tests/__init__.py
multimatch/tests/test_MultiMatch.py
multimatch/tests/utils.py
multimatch-0.1.0.dist-info/LICENSE
multimatch-0.1.0.dist-info/METADATA
multimatch-0.1.0.dist-info/WHEEL
multimatch-0.1.0.dist-info/entry_points.txt
multimatch-0.1.0.dist-info/top_level.txt
multimatch-0.1.0.dist-info/RECORD
