Metadata-Version: 2.1
Name: multimatch
Version: 0.1.0
Summary: Multidimensional scanpath comparison
Home-page: https://github.com/adswa/multimatch
Author: Adina Wagner
Author-email: adina.wagner@t-online.de
License: UNKNOWN
Platform: UNKNOWN
Classifier: Programming Language :: Python :: 3
Classifier: License :: OSI Approved :: MIT License
Classifier: Operating System :: OS Independent
Requires-Dist: numpy
Requires-Dist: pandas
Provides-Extra: devel-docs
Requires-Dist: pypandoc ; extra == 'devel-docs'
